thesoup/utilityclasses/__init__.py
thesoup/utilityclasses/binarytree.py
thesoup/utilityclasses/disjointsets.py
thesoup/utilityclasses/graph.py
thesoup/utilityclasses/heap.py
thesoup/utilityclasses/result.py
thesoup/utilityclasses/sets.py
thesoup/utilityclasses/trie.py
thesoup/utilityfunctions/__init__.py
thesoup/utilityfunctions/collectionutils.py
thesoup/utilityfunctions/graphtraversals.py
thesoup/utilityfunctions/graphutils.py
thesoup/utilityfunctions/merge.py
thesoup/utilityfunctions/stringutils.py
thesoup-0.11.dist-info/LICENSE
thesoup-0.11.dist-info/METADATA
thesoup-0.11.dist-info/WHEEL
thesoup-0.11.dist-info/top_level.txt
thesoup-0.11.dist-info/RECORD
