Metadata-Version: 2.1
Name: thesoup
Version: 0.11
Summary: A soup of random python utils
Home-page: https://github.com/amartya00/thesoup
Author: Amartya Datta Gupta
Author-email: amartya00@gmail.com
License: GPLv2
Project-URL: Source, https://github.com/amartya00/thesoup
Platform: UNKNOWN
Classifier: Development Status :: 4 - Beta
Classifier: Intended Audience :: Developers
Classifier: Topic :: Software Development
Classifier: License :: OSI Approved :: GNU General Public License v2 (GPLv2)
Classifier: Programming Language :: Python :: 3.9
Provides-Extra: dev
Provides-Extra: test
Requires-Dist: nose ; extra == 'test'
